[
    {
        "alter": 12,
        "anzahl": 12,
        "bezeichnung": "Elefant",
        "durschnittsgewicht": 1300.0,
        "fellfarbe": "blau",
        "gefaehrdet": true,
        "raubtier": false,
        "rudeltier": true,
        "tragzeit": 12,
        "typ": "Saeugetier"
    },
    {
        "alter": 5,
        "anzahl": 2,
        "bezeichnung": "Capybara",
        "durschnittsgewicht": 300.0,
        "fellfarbe": "braun",
        "gefaehrdet": false,
        "raubtier": true,
        "rudeltier": false,
        "tragzeit": 3,
        "typ": "Saeugetier"
    },
    {
        "alter": 1,
        "anzahl": 5,
        "bezeichnung": "Maus",
        "durschnittsgewicht": 1.0,
        "fellfarbe": "grau",
        "gefaehrdet": false,
        "raubtier": true,
        "rudeltier": true,
        "tragzeit": 2,
        "typ": "Saeugetier"
    },
    {
        "alter": 2,
        "anzahl": 78,
        "bezeichnung": "Schlange",
        "gefaehrdet": false,
        "giftig": true,
        "optimale Temperatur": 15.0,
        "raubtier": false,
        "typ": "Reptil",
        "wechselwarm": true
    },
    {
        "alter": 3,
        "anzahl": 1,
        "bezeichnung": "Drachen",
        "gefaehrdet": true,
        "giftig": false,
        "optimale Temperatur": 25.0,
        "raubtier": false,
        "typ": "Reptil",
        "wechselwarm": true
    },
    {
        "alter": 2,
        "anzahl": 23,
        "bezeichnung": "Lizard",
        "gefaehrdet": false,
        "giftig": false,
        "optimale Temperatur": 20.0,
        "raubtier": false,
        "typ": "Reptil",
        "wechselwarm": true
    },
    {
        "alter": 1,
        "anzahl": 89,
        "bezeichnung": "Hühn",
        "fluegelspannweite": 20.0,
        "flugreichweite": 0.05,
        "gefaehrdet": false,
        "raubtier": false,
        "typ": "Vogel",
        "zugvogel": false
    },
    {
        "alter": 3,
        "anzahl": 2,
        "bezeichnung": "Pinguin",
        "fluegelspannweite": 50.0,
        "flugreichweite": 0.0,
        "gefaehrdet": true,
        "raubtier": false,
        "typ": "Vogel",
        "zugvogel": false
    },
    {
        "alter": 1,
        "anzahl": 45,
        "bezeichnung": "Pigeon",
        "fluegelspannweite": 15.0,
        "flugreichweite": 20.0,
        "gefaehrdet": false,
        "raubtier": true,
        "typ": "Vogel",
        "zugvogel": false
    }
]
